README.md
setup.py
employeesystem/employeesys.py
employeesystem.egg-info/PKG-INFO
employeesystem.egg-info/SOURCES.txt
employeesystem.egg-info/dependency_links.txt
employeesystem.egg-info/top_level.txt