Metadata-Version: 2.1
Name: employeesystem
Version: 1.1.3
Summary: Manage your workplace employees
Author: Grayson Huey
Author-email: graysonhuey02@gmail.com
Classifier: Programming Language :: Python :: 3
Classifier: License :: Free For Educational Use
Classifier: Operating System :: OS Independent
Requires-Python: >=3.6
